{
  "agent_id": "sample_68",
  "demographics": {
    "age": 34,
    "income": "$30,000 - $60,000",
    "education": "master's degree or higher",
    "occupation": "service worker",
    "housing": "renter"
  },
  "nodes": {
    "n1": {
      "label": "urban_density",
      "type": "continuous",
      "range": [
        0.0,
        1.0
      ],
      "semantic_role": "external_state",
      "appearance": {
        "qa_ids": [
          "qa_01",
          "qa_02"
        ],
        "frequency": 1
      },
      "incoming_edges": [],
      "outgoing_edges": [
        "e1",
        "e2"
      ]
    },
    "n2": {
      "label": "tax_base_diversity",
      "type": "continuous",
      "range": [
        0.0,
        1.0
      ],
      "semantic_role": "external_state",
      "appearance": {
        "qa_ids": [
          "qa_01",
          "qa_03"
        ],
        "frequency": 1
      },
      "incoming_edges": [
        "e1"
      ],
      "outgoing_edges": [
        "e3"
      ]
    },
    "n3": {
      "label": "infrastructure_funding",
      "type": "continuous",
      "range": [
        0.0,
        1.0
      ],
      "semantic_role": "external_state",
      "appearance": {
        "qa_ids": [
          "qa_02",
          "qa_04"
        ],
        "frequency": 1
      },
      "incoming_edges": [
        "e2"
      ],
      "outgoing_edges": [
        "e4"
      ]
    },
    "n4": {
      "label": "governance_stability",
      "type": "continuous",
      "range": [
        0.0,
        1.0
      ],
      "semantic_role": "external_state",
      "appearance": {
        "qa_ids": [
          "qa_03",
          "qa_05"
        ],
        "frequency": 1
      },
      "incoming_edges": [
        "e3"
      ],
      "outgoing_edges": [
        "e5"
      ]
    },
    "n5": {
      "label": "debt_management",
      "type": "continuous",
      "range": [
        0.0,
        1.0
      ],
      "semantic_role": "external_state",
      "appearance": {
        "qa_ids": [
          "qa_04",
          "qa_06"
        ],
        "frequency": 1
      },
      "incoming_edges": [
        "e4"
      ],
      "outgoing_edges": [
        "e6"
      ]
    },
    "n6": {
      "label": "economic_resilience",
      "type": "continuous",
      "range": [
        0.0,
        1.0
      ],
      "semantic_role": "internal_affect",
      "appearance": {
        "qa_ids": [
          "qa_05",
          "qa_07"
        ],
        "frequency": 1
      },
      "incoming_edges": [
        "e5",
        "e6"
      ],
      "outgoing_edges": [
        "e7"
      ]
    },
    "n7": {
      "label": "demographic_trends",
      "type": "continuous",
      "range": [
        0.0,
        1.0
      ],
      "semantic_role": "internal_affect",
      "appearance": {
        "qa_ids": [
          "qa_07",
          "qa_08"
        ],
        "frequency": 1
      },
      "incoming_edges": [
        "e7"
      ],
      "outgoing_edges": [
        "e8"
      ]
    },
    "n8": {
      "label": "public_services",
      "type": "continuous",
      "range": [
        0.0,
        1.0
      ],
      "semantic_role": "internal_affect",
      "appearance": {
        "qa_ids": [
          "qa_08",
          "qa_09"
        ],
        "frequency": 1
      },
      "incoming_edges": [
        "e8"
      ],
      "outgoing_edges": [
        "e9"
      ]
    },
    "n9": {
      "label": "real_estate_values",
      "type": "continuous",
      "range": [
        0.0,
        1.0
      ],
      "semantic_role": "internal_affect",
      "appearance": {
        "qa_ids": [
          "qa_09",
          "qa_10"
        ],
        "frequency": 1
      },
      "incoming_edges": [
        "e9"
      ],
      "outgoing_edges": [
        "e10"
      ]
    },
    "n10": {
      "label": "commercial_activity",
      "type": "continuous",
      "range": [
        0.0,
        1.0
      ],
      "semantic_role": "internal_affect",
      "appearance": {
        "qa_ids": [
          "qa_10",
          "qa_11"
        ],
        "frequency": 1
      },
      "incoming_edges": [
        "e10"
      ],
      "outgoing_edges": [
        "e11"
      ]
    },
    "n11": {
      "label": "employment_opportunities",
      "type": "continuous",
      "range": [
        0.0,
        1.0
      ],
      "semantic_role": "internal_affect",
      "appearance": {
        "qa_ids": [
          "qa_11",
          "qa_12"
        ],
        "frequency": 1
      },
      "incoming_edges": [
        "e11"
      ],
      "outgoing_edges": [
        "e12"
      ]
    },
    "n12": {
      "label": "investment_attractiveness",
      "type": "continuous",
      "range": [
        0.0,
        1.0
      ],
      "semantic_role": "internal_affect",
      "appearance": {
        "qa_ids": [
          "qa_12",
          "qa_13"
        ],
        "frequency": 1
      },
      "incoming_edges": [
        "e12"
      ],
      "outgoing_edges": [
        "e13"
      ]
    },
    "n13": {
      "label": "long_term_growth",
      "type": "continuous",
      "range": [
        0.0,
        1.0
      ],
      "semantic_role": "internal_affect",
      "appearance": {
        "qa_ids": [
          "qa_13",
          "qa_14"
        ],
        "frequency": 1
      },
      "incoming_edges": [
        "e13"
      ],
      "outgoing_edges": [
        "e14"
      ]
    },
    "n14": {
      "label": "risk_assessment",
      "type": "binary",
      "values": [
        true,
        false
      ],
      "semantic_role": "internal_affect",
      "appearance": {
        "qa_ids": [
          "qa_14",
          "qa_15"
        ],
        "frequency": 1
      },
      "incoming_edges": [
        "e14"
      ],
      "outgoing_edges": [
        "e15"
      ]
    },
    "n15": {
      "label": "upzoning_stance",
      "type": "binary",
      "values": [
        true,
        false
      ],
      "semantic_role": "behavioral_intention",
      "appearance": {
        "qa_ids": [
          "qa_15"
        ],
        "frequency": 1
      },
      "incoming_edges": [
        "e15"
      ],
      "outgoing_edges": []
    }
  },
  "edges": {
    "e1": {
      "from": "n1",
      "to": "n2",
      "function": {
        "target": "n2",
        "inputs": [
          "n1"
        ],
        "function_type": "sigmoid",
        "parameters": {
          "weights": [
            0.8
          ],
          "bias": -0.2
        },
        "noise_std": 0.1,
        "support_qas": [
          "qa_01"
        ],
        "confidence": 0.9
      },
      "support_qas": [
        "qa_01"
      ]
    },
    "e2": {
      "from": "n1",
      "to": "n3",
      "function": {
        "target": "n3",
        "inputs": [
          "n1"
        ],
        "function_type": "sigmoid",
        "parameters": {
          "weights": [
            0.8
          ],
          "bias": -0.2
        },
        "noise_std": 0.1,
        "support_qas": [
          "qa_02"
        ],
        "confidence": 0.9
      },
      "support_qas": [
        "qa_02"
      ]
    },
    "e3": {
      "from": "n2",
      "to": "n4",
      "function": {
        "target": "n4",
        "inputs": [
          "n2"
        ],
        "function_type": "sigmoid",
        "parameters": {
          "weights": [
            0.8
          ],
          "bias": -0.2
        },
        "noise_std": 0.1,
        "support_qas": [
          "qa_03"
        ],
        "confidence": 0.9
      },
      "support_qas": [
        "qa_03"
      ]
    },
    "e4": {
      "from": "n3",
      "to": "n5",
      "function": {
        "target": "n5",
        "inputs": [
          "n3"
        ],
        "function_type": "sigmoid",
        "parameters": {
          "weights": [
            0.8
          ],
          "bias": -0.2
        },
        "noise_std": 0.1,
        "support_qas": [
          "qa_04"
        ],
        "confidence": 0.9
      },
      "support_qas": [
        "qa_04"
      ]
    },
    "e5": {
      "from": "n4",
      "to": "n6",
      "function": {
        "target": "n6",
        "inputs": [
          "n4"
        ],
        "function_type": "sigmoid",
        "parameters": {
          "weights": [
            0.8
          ],
          "bias": -0.2
        },
        "noise_std": 0.1,
        "support_qas": [
          "qa_05"
        ],
        "confidence": 0.9
      },
      "support_qas": [
        "qa_05"
      ]
    },
    "e6": {
      "from": "n5",
      "to": "n6",
      "function": {
        "target": "n6",
        "inputs": [
          "n5"
        ],
        "function_type": "sigmoid",
        "parameters": {
          "weights": [
            0.8
          ],
          "bias": -0.2
        },
        "noise_std": 0.1,
        "support_qas": [
          "qa_06"
        ],
        "confidence": 0.9
      },
      "support_qas": [
        "qa_06"
      ]
    },
    "e7": {
      "from": "n6",
      "to": "n7",
      "function": {
        "target": "n7",
        "inputs": [
          "n6"
        ],
        "function_type": "sigmoid",
        "parameters": {
          "weights": [
            0.8
          ],
          "bias": -0.2
        },
        "noise_std": 0.1,
        "support_qas": [
          "qa_07"
        ],
        "confidence": 0.9
      },
      "support_qas": [
        "qa_07"
      ]
    },
    "e8": {
      "from": "n7",
      "to": "n8",
      "function": {
        "target": "n8",
        "inputs": [
          "n7"
        ],
        "function_type": "sigmoid",
        "parameters": {
          "weights": [
            0.8
          ],
          "bias": -0.2
        },
        "noise_std": 0.1,
        "support_qas": [
          "qa_08"
        ],
        "confidence": 0.9
      },
      "support_qas": [
        "qa_08"
      ]
    },
    "e9": {
      "from": "n8",
      "to": "n9",
      "function": {
        "target": "n9",
        "inputs": [
          "n8"
        ],
        "function_type": "sigmoid",
        "parameters": {
          "weights": [
            0.8
          ],
          "bias": -0.2
        },
        "noise_std": 0.1,
        "support_qas": [
          "qa_09"
        ],
        "confidence": 0.9
      },
      "support_qas": [
        "qa_09"
      ]
    },
    "e10": {
      "from": "n9",
      "to": "n10",
      "function": {
        "target": "n10",
        "inputs": [
          "n9"
        ],
        "function_type": "sigmoid",
        "parameters": {
          "weights": [
            0.8
          ],
          "bias": -0.2
        },
        "noise_std": 0.1,
        "support_qas": [
          "qa_10"
        ],
        "confidence": 0.9
      },
      "support_qas": [
        "qa_10"
      ]
    },
    "e11": {
      "from": "n10",
      "to": "n11",
      "function": {
        "target": "n11",
        "inputs": [
          "n10"
        ],
        "function_type": "sigmoid",
        "parameters": {
          "weights": [
            0.8
          ],
          "bias": -0.2
        },
        "noise_std": 0.1,
        "support_qas": [
          "qa_11"
        ],
        "confidence": 0.9
      },
      "support_qas": [
        "qa_11"
      ]
    },
    "e12": {
      "from": "n11",
      "to": "n12",
      "function": {
        "target": "n12",
        "inputs": [
          "n11"
        ],
        "function_type": "sigmoid",
        "parameters": {
          "weights": [
            0.8
          ],
          "bias": -0.2
        },
        "noise_std": 0.1,
        "support_qas": [
          "qa_12"
        ],
        "confidence": 0.9
      },
      "support_qas": [
        "qa_12"
      ]
    },
    "e13": {
      "from": "n12",
      "to": "n13",
      "function": {
        "target": "n13",
        "inputs": [
          "n12"
        ],
        "function_type": "sigmoid",
        "parameters": {
          "weights": [
            0.8
          ],
          "bias": -0.2
        },
        "noise_std": 0.1,
        "support_qas": [
          "qa_13"
        ],
        "confidence": 0.9
      },
      "support_qas": [
        "qa_13"
      ]
    },
    "e14": {
      "from": "n13",
      "to": "n14",
      "function": {
        "target": "n14",
        "inputs": [
          "n13"
        ],
        "function_type": "threshold",
        "parameters": {
          "threshold": 0.6,
          "direction": "greater"
        },
        "noise_std": 0.1,
        "support_qas": [
          "qa_14"
        ],
        "confidence": 0.9
      },
      "support_qas": [
        "qa_14"
      ]
    },
    "e15": {
      "from": "n14",
      "to": "n15",
      "function": {
        "target": "n15",
        "inputs": [
          "n14"
        ],
        "function_type": "threshold",
        "parameters": {
          "threshold": 0.6,
          "direction": "less"
        },
        "noise_std": 0.1,
        "support_qas": [
          "qa_15"
        ],
        "confidence": 0.9
      },
      "support_qas": [
        "qa_15"
      ]
    }
  },
  "qas": [
    {
      "qa_id": "qa_01",
      "question": "How does urban density affect tax base diversity?",
      "answer": "Higher urban density leads to a more diverse tax base because it attracts a variety of businesses and residents, which in turn increases the range of taxes collected.",
      "parsed_belief": {
        "belief_structure": {
          "from": "n1",
          "to": "n2",
          "direction": "positive"
        },
        "belief_strength": {
          "estimated_probability": 0.8,
          "confidence_rating": 0.9
        },
        "counterfactual": "If urban density were lower, the tax base would be less diverse."
      }
    },
    {
      "qa_id": "qa_02",
      "question": "How does urban density impact infrastructure funding?",
      "answer": "Higher urban density can lead to increased infrastructure funding as more people and businesses contribute to the local economy, allowing for greater investment in public infrastructure.",
      "parsed_belief": {
        "belief_structure": {
          "from": "n1",
          "to": "n3",
          "direction": "positive"
        },
        "belief_strength": {
          "estimated_probability": 0.8,
          "confidence_rating": 0.9
        },
        "counterfactual": "If urban density were lower, there would be less funding for infrastructure."
      }
    },
    {
      "qa_id": "qa_03",
      "question": "How does tax base diversity influence governance stability?",
      "answer": "A more diverse tax base contributes to governance stability by providing a more stable and predictable revenue stream, which helps in planning and budgeting.",
      "parsed_belief": {
        "belief_structure": {
          "from": "n2",
          "to": "n4",
          "direction": "positive"
        },
        "belief_strength": {
          "estimated_probability": 0.8,
          "confidence_rating": 0.9
        },
        "counterfactual": "If the tax base were less diverse, governance stability would be at risk due to unpredictable revenues."
      }
    },
    {
      "qa_id": "qa_04",
      "question": "How does infrastructure funding affect debt management?",
      "answer": "Increased infrastructure funding can improve debt management by allowing for better allocation of resources and reducing the need for high-interest borrowing.",
      "parsed_belief": {
        "belief_structure": {
          "from": "n3",
          "to": "n5",
          "direction": "positive"
        },
        "belief_strength": {
          "estimated_probability": 0.8,
          "confidence_rating": 0.9
        },
        "counterfactual": "If infrastructure funding were lower, debt management would be more challenging."
      }
    },
    {
      "qa_id": "qa_05",
      "question": "How does governance stability contribute to economic resilience?",
      "answer": "Governance stability enhances economic resilience by creating a predictable and reliable environment for businesses and investors, which fosters long-term growth and stability.",
      "parsed_belief": {
        "belief_structure": {
          "from": "n4",
          "to": "n6",
          "direction": "positive"
        },
        "belief_strength": {
          "estimated_probability": 0.8,
          "confidence_rating": 0.9
        },
        "counterfactual": "If governance were unstable, economic resilience would suffer."
      }
    },
    {
      "qa_id": "qa_06",
      "question": "How does effective debt management support economic resilience?",
      "answer": "Effective debt management ensures that financial resources are used efficiently, reducing the burden on the economy and enhancing its ability to withstand economic shocks.",
      "parsed_belief": {
        "belief_structure": {
          "from": "n5",
          "to": "n6",
          "direction": "positive"
        },
        "belief_strength": {
          "estimated_probability": 0.8,
          "confidence_rating": 0.9
        },
        "counterfactual": "If debt management were poor, economic resilience would be compromised."
      }
    },
    {
      "qa_id": "qa_07",
      "question": "How does economic resilience influence demographic trends?",
      "answer": "Economic resilience attracts and retains a diverse population, including young professionals and families, which positively influences demographic trends and supports a growing and vibrant community.",
      "parsed_belief": {
        "belief_structure": {
          "from": "n6",
          "to": "n7",
          "direction": "positive"
        },
        "belief_strength": {
          "estimated_probability": 0.8,
          "confidence_rating": 0.9
        },
        "counterfactual": "If economic resilience were low, demographic trends would be less favorable."
      }
    },
    {
      "qa_id": "qa_08",
      "question": "How do demographic trends affect public services?",
      "answer": "Positive demographic trends, such as a growing and diverse population, lead to increased demand and support for public services, which in turn improves the quality and availability of these services.",
      "parsed_belief": {
        "belief_structure": {
          "from": "n7",
          "to": "n8",
          "direction": "positive"
        },
        "belief_strength": {
          "estimated_probability": 0.8,
          "confidence_rating": 0.9
        },
        "counterfactual": "If demographic trends were negative, public services would suffer."
      }
    },
    {
      "qa_id": "qa_09",
      "question": "How do public services impact real estate values?",
      "answer": "High-quality public services, such as good schools and efficient transportation, increase the desirability of an area, leading to higher real estate values.",
      "parsed_belief": {
        "belief_structure": {
          "from": "n8",
          "to": "n9",
          "direction": "positive"
        },
        "belief_strength": {
          "estimated_probability": 0.8,
          "confidence_rating": 0.9
        },
        "counterfactual": "If public services were poor, real estate values would be lower."
      }
    },
    {
      "qa_id": "qa_10",
      "question": "How do real estate values influence commercial activity?",
      "answer": "Higher real estate values attract more businesses and investments, leading to increased commercial activity and a thriving local economy.",
      "parsed_belief": {
        "belief_structure": {
          "from": "n9",
          "to": "n10",
          "direction": "positive"
        },
        "belief_strength": {
          "estimated_probability": 0.8,
          "confidence_rating": 0.9
        },
        "counterfactual": "If real estate values were low, commercial activity would be limited."
      }
    },
    {
      "qa_id": "qa_11",
      "question": "How does commercial activity affect employment opportunities?",
      "answer": "Increased commercial activity creates more jobs and business opportunities, leading to better employment prospects for residents.",
      "parsed_belief": {
        "belief_structure": {
          "from": "n10",
          "to": "n11",
          "direction": "positive"
        },
        "belief_strength": {
          "estimated_probability": 0.8,
          "confidence_rating": 0.9
        },
        "counterfactual": "If commercial activity were low, employment opportunities would be fewer."
      }
    },
    {
      "qa_id": "qa_12",
      "question": "How do employment opportunities impact investment attractiveness?",
      "answer": "More employment opportunities make an area more attractive for investment, as it indicates a strong and growing local economy, which is appealing to both local and external investors.",
      "parsed_belief": {
        "belief_structure": {
          "from": "n11",
          "to": "n12",
          "direction": "positive"
        },
        "belief_strength": {
          "estimated_probability": 0.8,
          "confidence_rating": 0.9
        },
        "counterfactual": "If employment opportunities were scarce, investment attractiveness would be lower."
      }
    },
    {
      "qa_id": "qa_13",
      "question": "How does investment attractiveness contribute to long-term growth?",
      "answer": "High investment attractiveness leads to sustained economic growth by bringing in new capital, technology, and talent, which drives innovation and development over the long term.",
      "parsed_belief": {
        "belief_structure": {
          "from": "n12",
          "to": "n13",
          "direction": "positive"
        },
        "belief_strength": {
          "estimated_probability": 0.8,
          "confidence_rating": 0.9
        },
        "counterfactual": "If investment attractiveness were low, long-term growth would be limited."
      }
    },
    {
      "qa_id": "qa_14",
      "question": "How does long-term growth affect risk assessment?",
      "answer": "Long-term growth reduces perceived risk, as it indicates a stable and growing economy, making the area more attractive for further investment and development.",
      "parsed_belief": {
        "belief_structure": {
          "from": "n13",
          "to": "n14",
          "direction": "positive"
        },
        "belief_strength": {
          "estimated_probability": 0.8,
          "confidence_rating": 0.9
        },
        "counterfactual": "If long-term growth were uncertain, risk assessment would be more cautious."
      }
    },
    {
      "qa_id": "qa_15",
      "question": "How does risk assessment influence upzoning stance?",
      "answer": "A positive risk assessment, indicating a low-risk and stable environment, may lead to a more favorable stance on upzoning, as it suggests that the area can handle increased density and development without significant negative impacts.",
      "parsed_belief": {
        "belief_structure": {
          "from": "n14",
          "to": "n15",
          "direction": "negative"
        },
        "belief_strength": {
          "estimated_probability": 0.8,
          "confidence_rating": 0.9
        },
        "counterfactual": "If the risk assessment were negative, the upzoning stance would likely be more cautious."
      }
    }
  ]
}