{
  "agent_id": "sample_40",
  "demographics": {
    "age": 37,
    "income": "$60,000 - $100,000",
    "education": "master's degree or higher",
    "occupation": "technician",
    "housing": "lives with family"
  },
  "nodes": {
    "n1": {
      "label": "density",
      "type": "continuous",
      "range": [
        0.0,
        1.0
      ],
      "semantic_role": "external_state",
      "appearance": {
        "qa_ids": [
          "qa_01",
          "qa_02"
        ],
        "frequency": 1
      },
      "incoming_edges": [],
      "outgoing_edges": [
        "e1",
        "e2",
        "e15"
      ]
    },
    "n2": {
      "label": "walkability",
      "type": "continuous",
      "range": [
        0.0,
        1.0
      ],
      "semantic_role": "external_state",
      "appearance": {
        "qa_ids": [
          "qa_03",
          "qa_04"
        ],
        "frequency": 1
      },
      "incoming_edges": [
        "e1"
      ],
      "outgoing_edges": [
        "e3",
        "e4"
      ]
    },
    "n3": {
      "label": "social_venues",
      "type": "continuous",
      "range": [
        0.0,
        1.0
      ],
      "semantic_role": "external_state",
      "appearance": {
        "qa_ids": [
          "qa_05",
          "qa_06"
        ],
        "frequency": 1
      },
      "incoming_edges": [
        "e2"
      ],
      "outgoing_edges": [
        "e5",
        "e6"
      ]
    },
    "n4": {
      "label": "lifestyle_convenience",
      "type": "continuous",
      "range": [
        0.0,
        1.0
      ],
      "semantic_role": "internal_affect",
      "appearance": {
        "qa_ids": [
          "qa_07",
          "qa_08"
        ],
        "frequency": 1
      },
      "incoming_edges": [
        "e3"
      ],
      "outgoing_edges": [
        "e7"
      ]
    },
    "n5": {
      "label": "work_opportunities",
      "type": "binary",
      "values": [
        true,
        false
      ],
      "semantic_role": "external_state",
      "appearance": {
        "qa_ids": [
          "qa_09",
          "qa_10"
        ],
        "frequency": 1
      },
      "incoming_edges": [],
      "outgoing_edges": [
        "e8"
      ]
    },
    "n6": {
      "label": "cultural_options",
      "type": "binary",
      "values": [
        true,
        false
      ],
      "semantic_role": "external_state",
      "appearance": {
        "qa_ids": [
          "qa_11",
          "qa_12"
        ],
        "frequency": 1
      },
      "incoming_edges": [],
      "outgoing_edges": [
        "e9"
      ]
    },
    "n7": {
      "label": "recreational_options",
      "type": "binary",
      "values": [
        true,
        false
      ],
      "semantic_role": "external_state",
      "appearance": {
        "qa_ids": [
          "qa_13",
          "qa_14"
        ],
        "frequency": 1
      },
      "incoming_edges": [],
      "outgoing_edges": [
        "e10"
      ]
    },
    "n8": {
      "label": "transportation_efficiency",
      "type": "continuous",
      "range": [
        0.0,
        1.0
      ],
      "semantic_role": "external_state",
      "appearance": {
        "qa_ids": [
          "qa_15",
          "qa_16"
        ],
        "frequency": 1
      },
      "incoming_edges": [
        "e15"
      ],
      "outgoing_edges": [
        "e11"
      ]
    },
    "n9": {
      "label": "non_work_activities",
      "type": "continuous",
      "range": [
        0.0,
        1.0
      ],
      "semantic_role": "internal_affect",
      "appearance": {
        "qa_ids": [
          "qa_17",
          "qa_18"
        ],
        "frequency": 1
      },
      "incoming_edges": [
        "e11"
      ],
      "outgoing_edges": [
        "e12"
      ]
    },
    "n10": {
      "label": "personal_network",
      "type": "continuous",
      "range": [
        0.0,
        1.0
      ],
      "semantic_role": "internal_affect",
      "appearance": {
        "qa_ids": [
          "qa_19",
          "qa_20"
        ],
        "frequency": 1
      },
      "incoming_edges": [
        "e5"
      ],
      "outgoing_edges": [
        "e13"
      ]
    },
    "n11": {
      "label": "urban_vitality",
      "type": "continuous",
      "range": [
        0.0,
        1.0
      ],
      "semantic_role": "internal_affect",
      "appearance": {
        "qa_ids": [
          "qa_21",
          "qa_22"
        ],
        "frequency": 1
      },
      "incoming_edges": [
        "e4",
        "e6"
      ],
      "outgoing_edges": [
        "e14"
      ]
    },
    "n12": {
      "label": "quality_of_life",
      "type": "continuous",
      "range": [
        0.0,
        1.0
      ],
      "semantic_role": "behavioral_intention",
      "appearance": {
        "qa_ids": [
          "qa_23",
          "qa_24"
        ],
        "frequency": 1
      },
      "incoming_edges": [
        "e7",
        "e8",
        "e9",
        "e10",
        "e12",
        "e13",
        "e14"
      ],
      "outgoing_edges": [
        "e16"
      ]
    },
    "n13": {
      "label": "upzoning_stance",
      "type": "binary",
      "values": [
        true,
        false
      ],
      "semantic_role": "behavioral_intention",
      "appearance": {
        "qa_ids": [
          "qa_25",
          "qa_26"
        ],
        "frequency": 1
      },
      "incoming_edges": [
        "e16"
      ],
      "outgoing_edges": []
    }
  },
  "edges": {
    "e1": {
      "from": "n1",
      "to": "n2",
      "function": {
        "target": "n2",
        "inputs": [
          "n1"
        ],
        "function_type": "sigmoid",
        "parameters": {
          "weights": [
            0.8
          ],
          "bias": -0.2
        },
        "noise_std": 0.1,
        "support_qas": [
          "qa_01"
        ],
        "confidence": 0.9
      },
      "support_qas": [
        "qa_01"
      ]
    },
    "e2": {
      "from": "n1",
      "to": "n3",
      "function": {
        "target": "n3",
        "inputs": [
          "n1"
        ],
        "function_type": "sigmoid",
        "parameters": {
          "weights": [
            0.8
          ],
          "bias": -0.2
        },
        "noise_std": 0.1,
        "support_qas": [
          "qa_02"
        ],
        "confidence": 0.9
      },
      "support_qas": [
        "qa_02"
      ]
    },
    "e3": {
      "from": "n2",
      "to": "n4",
      "function": {
        "target": "n4",
        "inputs": [
          "n2"
        ],
        "function_type": "sigmoid",
        "parameters": {
          "weights": [
            0.8
          ],
          "bias": -0.2
        },
        "noise_std": 0.1,
        "support_qas": [
          "qa_03"
        ],
        "confidence": 0.9
      },
      "support_qas": [
        "qa_03"
      ]
    },
    "e4": {
      "from": "n2",
      "to": "n11",
      "function": {
        "target": "n11",
        "inputs": [
          "n2"
        ],
        "function_type": "sigmoid",
        "parameters": {
          "weights": [
            0.8
          ],
          "bias": -0.2
        },
        "noise_std": 0.1,
        "support_qas": [
          "qa_04"
        ],
        "confidence": 0.9
      },
      "support_qas": [
        "qa_04"
      ]
    },
    "e5": {
      "from": "n3",
      "to": "n10",
      "function": {
        "target": "n10",
        "inputs": [
          "n3"
        ],
        "function_type": "sigmoid",
        "parameters": {
          "weights": [
            0.8
          ],
          "bias": -0.2
        },
        "noise_std": 0.1,
        "support_qas": [
          "qa_05"
        ],
        "confidence": 0.9
      },
      "support_qas": [
        "qa_05"
      ]
    },
    "e6": {
      "from": "n3",
      "to": "n11",
      "function": {
        "target": "n11",
        "inputs": [
          "n3"
        ],
        "function_type": "sigmoid",
        "parameters": {
          "weights": [
            0.8
          ],
          "bias": -0.2
        },
        "noise_std": 0.1,
        "support_qas": [
          "qa_06"
        ],
        "confidence": 0.9
      },
      "support_qas": [
        "qa_06"
      ]
    },
    "e7": {
      "from": "n4",
      "to": "n12",
      "function": {
        "target": "n12",
        "inputs": [
          "n4"
        ],
        "function_type": "sigmoid",
        "parameters": {
          "weights": [
            0.8
          ],
          "bias": -0.2
        },
        "noise_std": 0.1,
        "support_qas": [
          "qa_07"
        ],
        "confidence": 0.9
      },
      "support_qas": [
        "qa_07"
      ]
    },
    "e8": {
      "from": "n5",
      "to": "n12",
      "function": {
        "target": "n12",
        "inputs": [
          "n5"
        ],
        "function_type": "threshold",
        "parameters": {
          "threshold": 0.6,
          "direction": "greater"
        },
        "noise_std": 0.1,
        "support_qas": [
          "qa_08"
        ],
        "confidence": 0.9
      },
      "support_qas": [
        "qa_08"
      ]
    },
    "e9": {
      "from": "n6",
      "to": "n12",
      "function": {
        "target": "n12",
        "inputs": [
          "n6"
        ],
        "function_type": "threshold",
        "parameters": {
          "threshold": 0.6,
          "direction": "greater"
        },
        "noise_std": 0.1,
        "support_qas": [
          "qa_09"
        ],
        "confidence": 0.9
      },
      "support_qas": [
        "qa_09"
      ]
    },
    "e10": {
      "from": "n7",
      "to": "n12",
      "function": {
        "target": "n12",
        "inputs": [
          "n7"
        ],
        "function_type": "threshold",
        "parameters": {
          "threshold": 0.6,
          "direction": "greater"
        },
        "noise_std": 0.1,
        "support_qas": [
          "qa_10"
        ],
        "confidence": 0.9
      },
      "support_qas": [
        "qa_10"
      ]
    },
    "e11": {
      "from": "n8",
      "to": "n9",
      "function": {
        "target": "n9",
        "inputs": [
          "n8"
        ],
        "function_type": "sigmoid",
        "parameters": {
          "weights": [
            0.8
          ],
          "bias": -0.2
        },
        "noise_std": 0.1,
        "support_qas": [
          "qa_11"
        ],
        "confidence": 0.9
      },
      "support_qas": [
        "qa_11"
      ]
    },
    "e12": {
      "from": "n9",
      "to": "n12",
      "function": {
        "target": "n12",
        "inputs": [
          "n9"
        ],
        "function_type": "sigmoid",
        "parameters": {
          "weights": [
            0.8
          ],
          "bias": -0.2
        },
        "noise_std": 0.1,
        "support_qas": [
          "qa_12"
        ],
        "confidence": 0.9
      },
      "support_qas": [
        "qa_12"
      ]
    },
    "e13": {
      "from": "n10",
      "to": "n12",
      "function": {
        "target": "n12",
        "inputs": [
          "n10"
        ],
        "function_type": "sigmoid",
        "parameters": {
          "weights": [
            0.8
          ],
          "bias": -0.2
        },
        "noise_std": 0.1,
        "support_qas": [
          "qa_13"
        ],
        "confidence": 0.9
      },
      "support_qas": [
        "qa_13"
      ]
    },
    "e14": {
      "from": "n11",
      "to": "n12",
      "function": {
        "target": "n12",
        "inputs": [
          "n11"
        ],
        "function_type": "sigmoid",
        "parameters": {
          "weights": [
            0.8
          ],
          "bias": -0.2
        },
        "noise_std": 0.1,
        "support_qas": [
          "qa_14"
        ],
        "confidence": 0.9
      },
      "support_qas": [
        "qa_14"
      ]
    },
    "e15": {
      "from": "n1",
      "to": "n8",
      "function": {
        "target": "n8",
        "inputs": [
          "n1"
        ],
        "function_type": "sigmoid",
        "parameters": {
          "weights": [
            -0.8
          ],
          "bias": 0.2
        },
        "noise_std": 0.1,
        "support_qas": [
          "qa_15"
        ],
        "confidence": 0.9
      },
      "support_qas": [
        "qa_15"
      ]
    },
    "e16": {
      "from": "n12",
      "to": "n13",
      "function": {
        "target": "n13",
        "inputs": [
          "n12"
        ],
        "function_type": "threshold",
        "parameters": {
          "threshold": 0.6,
          "direction": "less"
        },
        "noise_std": 0.1,
        "support_qas": [
          "qa_15"
        ],
        "confidence": 0.9
      },
      "support_qas": [
        "qa_15"
      ]
    }
  },
  "qas": [
    {
      "qa_id": "qa_01",
      "question": "How does urban density affect walkability?",
      "answer": "Higher urban density generally leads to better walkability because there are more destinations within walking distance.",
      "parsed_belief": {
        "belief_structure": {
          "from": "n1",
          "to": "n2",
          "direction": "positive"
        },
        "belief_strength": {
          "estimated_probability": 0.8,
          "confidence_rating": 0.9
        },
        "counterfactual": "If urban density were lower, then walkability would likely be worse."
      }
    },
    {
      "qa_id": "qa_02",
      "question": "How does urban density influence the availability of social venues?",
      "answer": "Higher urban density typically results in more social venues as there is a greater demand for such spaces.",
      "parsed_belief": {
        "belief_structure": {
          "from": "n1",
          "to": "n3",
          "direction": "positive"
        },
        "belief_strength": {
          "estimated_probability": 0.8,
          "confidence_rating": 0.9
        },
        "counterfactual": "If urban density were lower, then there would likely be fewer social venues."
      }
    },
    {
      "qa_id": "qa_03",
      "question": "How does walkability impact lifestyle convenience?",
      "answer": "Better walkability enhances lifestyle convenience by making it easier to access daily needs and services on foot.",
      "parsed_belief": {
        "belief_structure": {
          "from": "n2",
          "to": "n4",
          "direction": "positive"
        },
        "belief_strength": {
          "estimated_probability": 0.8,
          "confidence_rating": 0.9
        },
        "counterfactual": "If walkability were poor, then lifestyle convenience would likely be reduced."
      }
    },
    {
      "qa_id": "qa_04",
      "question": "How does walkability contribute to urban vitality?",
      "answer": "Good walkability contributes to urban vitality by fostering a vibrant and active street life.",
      "parsed_belief": {
        "belief_structure": {
          "from": "n2",
          "to": "n11",
          "direction": "positive"
        },
        "belief_strength": {
          "estimated_probability": 0.8,
          "confidence_rating": 0.9
        },
        "counterfactual": "If walkability were poor, then urban vitality would likely be diminished."
      }
    },
    {
      "qa_id": "qa_05",
      "question": "How do social venues impact personal networks?",
      "answer": "More social venues provide more opportunities to meet and interact with people, thus expanding personal networks.",
      "parsed_belief": {
        "belief_structure": {
          "from": "n3",
          "to": "n10",
          "direction": "positive"
        },
        "belief_strength": {
          "estimated_probability": 0.8,
          "confidence_rating": 0.9
        },
        "counterfactual": "If there were fewer social venues, then personal networks would likely be smaller."
      }
    },
    {
      "qa_id": "qa_06",
      "question": "How do social venues contribute to urban vitality?",
      "answer": "Social venues contribute to urban vitality by providing places for social interaction and community engagement.",
      "parsed_belief": {
        "belief_structure": {
          "from": "n3",
          "to": "n11",
          "direction": "positive"
        },
        "belief_strength": {
          "estimated_probability": 0.8,
          "confidence_rating": 0.9
        },
        "counterfactual": "If there were fewer social venues, then urban vitality would likely be reduced."
      }
    },
    {
      "qa_id": "qa_07",
      "question": "How does lifestyle convenience impact quality of life?",
      "answer": "Enhanced lifestyle convenience improves quality of life by making daily tasks and activities more manageable and enjoyable.",
      "parsed_belief": {
        "belief_structure": {
          "from": "n4",
          "to": "n12",
          "direction": "positive"
        },
        "belief_strength": {
          "estimated_probability": 0.8,
          "confidence_rating": 0.9
        },
        "counterfactual": "If lifestyle convenience were low, then quality of life would likely be negatively affected."
      }
    },
    {
      "qa_id": "qa_08",
      "question": "How do work opportunities influence quality of life?",
      "answer": "Having good work opportunities positively impacts quality of life by providing financial stability and career satisfaction.",
      "parsed_belief": {
        "belief_structure": {
          "from": "n5",
          "to": "n12",
          "direction": "positive"
        },
        "belief_strength": {
          "estimated_probability": 0.8,
          "confidence_rating": 0.9
        },
        "counterfactual": "If work opportunities were scarce, then quality of life would likely be lower."
      }
    },
    {
      "qa_id": "qa_09",
      "question": "How do cultural options impact quality of life?",
      "answer": "A wide range of cultural options enriches quality of life by offering diverse experiences and entertainment.",
      "parsed_belief": {
        "belief_structure": {
          "from": "n6",
          "to": "n12",
          "direction": "positive"
        },
        "belief_strength": {
          "estimated_probability": 0.8,
          "confidence_rating": 0.9
        },
        "counterfactual": "If cultural options were limited, then quality of life would likely be less enriched."
      }
    },
    {
      "qa_id": "qa_10",
      "question": "How do recreational options impact quality of life?",
      "answer": "Access to recreational options enhances quality of life by providing opportunities for leisure and physical activity.",
      "parsed_belief": {
        "belief_structure": {
          "from": "n7",
          "to": "n12",
          "direction": "positive"
        },
        "belief_strength": {
          "estimated_probability": 0.8,
          "confidence_rating": 0.9
        },
        "counterfactual": "If recreational options were limited, then quality of life would likely be reduced."
      }
    },
    {
      "qa_id": "qa_11",
      "question": "How does transportation efficiency impact non-work activities?",
      "answer": "Efficient transportation allows for more time and flexibility to engage in non-work activities, enhancing overall well-being.",
      "parsed_belief": {
        "belief_structure": {
          "from": "n8",
          "to": "n9",
          "direction": "positive"
        },
        "belief_strength": {
          "estimated_probability": 0.8,
          "confidence_rating": 0.9
        },
        "counterfactual": "If transportation efficiency were poor, then non-work activities would likely be more constrained."
      }
    },
    {
      "qa_id": "qa_12",
      "question": "How do non-work activities impact quality of life?",
      "answer": "Engaging in non-work activities contributes to a balanced and fulfilling life, thus improving quality of life.",
      "parsed_belief": {
        "belief_structure": {
          "from": "n9",
          "to": "n12",
          "direction": "positive"
        },
        "belief_strength": {
          "estimated_probability": 0.8,
          "confidence_rating": 0.9
        },
        "counterfactual": "If non-work activities were limited, then quality of life would likely be negatively affected."
      }
    },
    {
      "qa_id": "qa_13",
      "question": "How does a strong personal network impact quality of life?",
      "answer": "A strong personal network provides emotional support and social connections, which are crucial for a high quality of life.",
      "parsed_belief": {
        "belief_structure": {
          "from": "n10",
          "to": "n12",
          "direction": "positive"
        },
        "belief_strength": {
          "estimated_probability": 0.8,
          "confidence_rating": 0.9
        },
        "counterfactual": "If the personal network were weak, then quality of life would likely be lower."
      }
    },
    {
      "qa_id": "qa_14",
      "question": "How does urban vitality impact quality of life?",
      "answer": "High urban vitality creates a dynamic and engaging environment, which positively influences quality of life.",
      "parsed_belief": {
        "belief_structure": {
          "from": "n11",
          "to": "n12",
          "direction": "positive"
        },
        "belief_strength": {
          "estimated_probability": 0.8,
          "confidence_rating": 0.9
        },
        "counterfactual": "If urban vitality were low, then quality of life would likely be less dynamic and engaging."
      }
    },
    {
      "qa_id": "qa_15",
      "question": "How does urban density affect transportation efficiency?",
      "answer": "Higher urban density often leads to decreased transportation efficiency due to increased traffic and congestion.",
      "parsed_belief": {
        "belief_structure": {
          "from": "n1",
          "to": "n8",
          "direction": "negative"
        },
        "belief_strength": {
          "estimated_probability": 0.8,
          "confidence_rating": 0.9
        },
        "counterfactual": "If urban density were lower, then transportation efficiency would likely be better."
      }
    },
    {
      "qa_id": "qa_16",
      "question": "How does quality of life influence your stance on upzoning?",
      "answer": "If the quality of life is high, I am less likely to support upzoning, as I may be concerned about maintaining the current quality of life.",
      "parsed_belief": {
        "belief_structure": {
          "from": "n12",
          "to": "n13",
          "direction": "negative"
        },
        "belief_strength": {
          "estimated_probability": 0.8,
          "confidence_rating": 0.9
        },
        "counterfactual": "If the quality of life were lower, then I might be more open to upzoning to improve it."
      }
    }
  ]
}